pyrconcli/__init__.py
pyrconcli/__main__.py
pyrconcli-0.1.1.dist-info/LICENSE.md
pyrconcli-0.1.1.dist-info/METADATA
pyrconcli-0.1.1.dist-info/WHEEL
pyrconcli-0.1.1.dist-info/RECORD
