Metadata-Version: 2.1
Name: pyrconcli
Version: 0.1.1
Summary: 
License: GPL
Author: Grzegorz Koperwas
Author-email: admin@grzegorzkoperwas.site
Requires-Python: >=3.13,<4.0
Classifier: License :: Other/Proprietary License
Classifier: Programming Language :: Python :: 3
Requires-Dist: mcrcon (>=0.7.0,<0.8.0)
Requires-Dist: prompt-toolkit (>=3.0.48,<4.0.0)
